koji_fedoramessaging_messages/__init__.py
koji_fedoramessaging_messages/base.py
koji_fedoramessaging_messages/build.py
koji_fedoramessaging_messages/package.py
koji_fedoramessaging_messages/repo.py
koji_fedoramessaging_messages/rpm.py
koji_fedoramessaging_messages/tag.py
koji_fedoramessaging_messages/task.py
koji_fedoramessaging_messages/utilities.py
koji_fedoramessaging_messages-1.3.0.dist-info/METADATA
koji_fedoramessaging_messages-1.3.0.dist-info/WHEEL
koji_fedoramessaging_messages-1.3.0.dist-info/entry_points.txt
koji_fedoramessaging_messages-1.3.0.dist-info/licenses/LICENSES/GPL-3.0-or-later.txt
koji_fedoramessaging_messages-1.3.0.dist-info/RECORD
