Metadata-Version: 2.4
Name: koji-fedoramessaging-messages
Version: 1.3.0
Summary: A schema package for messages sent by the koji-fedoramessaging plugin
License: GPL-3.0-or-later
License-File: LICENSES/GPL-3.0-or-later.txt
Keywords: fedora
Author: Fedora Infrastructure Team
Author-email: infrastructure@lists.fedoraproject.org
Requires-Python: >=3.9,<4.0
Classifier: License :: OSI Approved :: GNU General Public License v3 or later (GPLv3+)
Classifier: Programming Language :: Python :: 3
Classifier: Programming Language :: Python :: 3.9
Classifier: Programming Language :: Python :: 3.10
Classifier: Programming Language :: Python :: 3.11
Classifier: Programming Language :: Python :: 3.12
Classifier: Programming Language :: Python :: 3.13
Classifier: Programming Language :: Python :: 3.14
Requires-Dist: fedora-messaging (>=3.0.1)
Project-URL: Homepage, https://github.com/fedora-infra/koji-fedoramessaging-messages
Project-URL: Repository, https://github.com/fedora-infra/koji-fedoramessaging-messages
